alu.v
module alu(
    input [7:0] a,
    input [7:0] b,
    input [2:0] sel,
    output reg [7:0] result
);

always @(*) begin
    case(sel)
        3'b000: result = a + b;     // Addition
        3'b001: result = a - b;     // Subtraction
        3'b010: result = a & b;     // AND
        3'b011: result = a | b;     // OR
        3'b100: result = a ^ b;     // XOR
        3'b101: result = ~a;        // NOT
        3'b110: result = a << 1;    // Left Shift
        3'b111: result = a >> 1;    // Right Shift
    endcase
end

endmodule

alu_tb.v
`timescale 1ns/1ps

module alu_tb;

reg [7:0] a;
reg [7:0] b;
reg [2:0] sel;
wire [7:0] result;

alu uut(
    .a(a),
    .b(b),
    .sel(sel),
    .result(result)
);

initial begin

$dumpfile("alu.vcd");
$dumpvars(0,alu_tb);

a = 8'd10;
b = 8'd5;

sel=3'b000; #10;
sel=3'b001; #10;
sel=3'b010; #10;
sel=3'b011; #10;
sel=3'b100; #10;
sel=3'b101; #10;
sel=3'b110; #10;
sel=3'b111; #10;

$finish;

end

endmodule

alu.vcd
$date
	Thu Jul  9 21:11:03 2026
$end
$version
	Icarus Verilog
$end
$timescale
	1ps
$end
$scope module alu_tb $end
$var wire 8 ! result [7:0] $end
$var reg 8 " a [7:0] $end
$var reg 8 # b [7:0] $end
$var reg 3 $ sel [2:0] $end
$scope module uut $end
$var wire 8 % a [7:0] $end
$var wire 8 & b [7:0] $end
$var wire 3 ' sel [2:0] $end
$var reg 8 ( result [7:0] $end
$upscope $end
$upscope $end
$enddefinitions $end
$comment Show the parameter values. $end
$dumpall
$end
#0
$dumpvars
b1111 (
b0 '
b101 &
b1010 %
b0 $
b101 #
b1010 "
b1111 !
$end
#10000
b101 !
b101 (
b1 $
b1 '
#20000
b0 !
b0 (
b10 $
b10 '
#30000
b1111 !
b1111 (
b11 $
b11 '
#40000
b100 $
b100 '
#50000
b11110101 !
b11110101 (
b101 $
b101 '
#60000
b10100 !
b10100 (
b110 $
b110 '
#70000
b101 !
b101 (
b111 $
b111 '
